[
  {
    "Position": 1,
    "Team": "Brazil",
    "Games Played": 6,
    "Win": 5,
    "Draw": 1,
    "Loss": 0,
    "Goals For": 14,
    "Goals Against": 5,
    "Goal Difference": 9,
    "Points": 11
  },
  {
    "Position": 2,
    "Team": "Czechoslovakia",
    "Games Played": 6,
    "Win": 3,
    "Draw": 1,
    "Loss": 2,
    "Goals For": 7,
    "Goals Against": 7,
    "Goal Difference": 0,
    "Points": 7
  },
  {
    "Position": 3,
    "Team": "Chile",
    "Games Played": 6,
    "Win": 4,
    "Draw": 0,
    "Loss": 2,
    "Goals For": 10,
    "Goals Against": 8,
    "Goal Difference": 2,
    "Points": 8
  },
  {
    "Position": 4,
    "Team": "Yugoslavia",
    "Games Played": 6,
    "Win": 3,
    "Draw": 0,
    "Loss": 3,
    "Goals For": 10,
    "Goals Against": 7,
    "Goal Difference": 3,
    "Points": 6
  },
  {
    "Position": 5,
    "Team": "Hungary",
    "Games Played": 4,
    "Win": 2,
    "Draw": 1,
    "Loss": 1,
    "Goals For": 8,
    "Goals Against": 3,
    "Goal Difference": 5,
    "Points": 5
  },
  {
    "Position": 6,
    "Team": "Soviet Union",
    "Games Played": 4,
    "Win": 2,
    "Draw": 1,
    "Loss": 1,
    "Goals For": 9,
    "Goals Against": 7,
    "Goal Difference": 2,
    "Points": 5
  },
  {
    "Position": 7,
    "Team": "West Germany",
    "Games Played": 4,
    "Win": 2,
    "Draw": 1,
    "Loss": 1,
    "Goals For": 4,
    "Goals Against": 2,
    "Goal Difference": 2,
    "Points": 5
  },
  {
    "Position": 8,
    "Team": "England",
    "Games Played": 4,
    "Win": 1,
    "Draw": 1,
    "Loss": 2,
    "Goals For": 5,
    "Goals Against": 6,
    "Goal Difference": "−1",
    "Points": 3
  },
  {
    "Position": 9,
    "Team": "Italy",
    "Games Played": 3,
    "Win": 1,
    "Draw": 1,
    "Loss": 1,
    "Goals For": 3,
    "Goals Against": 2,
    "Goal Difference": 1,
    "Points": 3
  },
  {
    "Position": 10,
    "Team": "Argentina",
    "Games Played": 3,
    "Win": 1,
    "Draw": 1,
    "Loss": 1,
    "Goals For": 2,
    "Goals Against": 3,
    "Goal Difference": "−1",
    "Points": 3
  },
  {
    "Position": 11,
    "Team": "Mexico",
    "Games Played": 3,
    "Win": 1,
    "Draw": 0,
    "Loss": 2,
    "Goals For": 3,
    "Goals Against": 4,
    "Goal Difference": "−1",
    "Points": 2
  },
  {
    "Position": 12,
    "Team": "Spain",
    "Games Played": 3,
    "Win": 1,
    "Draw": 0,
    "Loss": 2,
    "Goals For": 2,
    "Goals Against": 3,
    "Goal Difference": "−1",
    "Points": 2
  },
  {
    "Position": 13,
    "Team": "Uruguay",
    "Games Played": 3,
    "Win": 1,
    "Draw": 0,
    "Loss": 2,
    "Goals For": 4,
    "Goals Against": 6,
    "Goal Difference": "−2",
    "Points": 2
  },
  {
    "Position": 14,
    "Team": "Colombia",
    "Games Played": 3,
    "Win": 0,
    "Draw": 1,
    "Loss": 2,
    "Goals For": 5,
    "Goals Against": 11,
    "Goal Difference": "−6",
    "Points": 1
  },
  {
    "Position": 15,
    "Team": "Bulgaria",
    "Games Played": 3,
    "Win": 0,
    "Draw": 1,
    "Loss": 2,
    "Goals For": 1,
    "Goals Against": 7,
    "Goal Difference": "−6",
    "Points": 1
  },
  {
    "Position": 16,
    "Team": "Switzerland",
    "Games Played": 3,
    "Win": 0,
    "Draw": 0,
    "Loss": 3,
    "Goals For": 2,
    "Goals Against": 8,
    "Goal Difference": "−6",
    "Points": 0
  }
]